Metadata-Version: 1.1
Name: date-filter-dash
Version: 0.0.5
Summary: the dash date filter
Home-page: UNKNOWN
Author: kalimuthu periyasamy <1995kalimuthu@gmail.com>
Author-email: UNKNOWN
License: MIT
Platform: UNKNOWN
Classifier: Framework :: Dash
